itk_viewer_remote_image/__about__.py
itk_viewer_remote_image/__init__.py
itk_viewer_remote_image/remote_zarr.py
itk_viewer_remote_image-0.0.1.dist-info/METADATA
itk_viewer_remote_image-0.0.1.dist-info/WHEEL
itk_viewer_remote_image-0.0.1.dist-info/RECORD
